thoryvos/GUI_helper.py
thoryvos/StyleSheets.py
thoryvos/UI_Functions.py
thoryvos/__init__.py
thoryvos/__main__.py
thoryvos/fonts.py
thoryvos/main_ui.py
thoryvos/splash_screen_ui.py
thoryvos/thoryvos.py
thoryvos/thoryvos_cli.py
thoryvos/thoryvos_crypto.py
thoryvos/thoryvos_driver.py
thoryvos/thoryvos_driver_gui.py
thoryvos/thoryvos_encoder.py
thoryvos/thoryvos_errorcodes.py
thoryvos/thoryvos_errors.py
thoryvos/thoryvos_stego.py
thoryvos/thoryvos_transfer.py
thoryvos/fonts/CFNightofTerrorPERSONAL-Reg.ttf
thoryvos/fonts/CabinSketch-Bold.ttf
thoryvos/fonts/CabinSketch-Regular.ttf
thoryvos/fonts/Courgette-Regular.ttf
thoryvos/fonts/DEADLY KILLERS.ttf
thoryvos/fonts/FEASFBI.ttf
thoryvos/fonts/FEASFBI_.ttf
thoryvos/fonts/FEASFBRG.ttf
thoryvos/fonts/Lemon-Regular.ttf
thoryvos/fonts/Martyric_PersonalUse.ttf
thoryvos/fonts/PirataOne-Regular.ttf
thoryvos/fonts/RW-creepsville.ttf
thoryvos/fonts/monbaiti.ttf
thoryvos-1.0.5.dist-info/LICENSE
thoryvos-1.0.5.dist-info/METADATA
thoryvos-1.0.5.dist-info/WHEEL
thoryvos-1.0.5.dist-info/entry_points.txt
thoryvos-1.0.5.dist-info/top_level.txt
thoryvos-1.0.5.dist-info/RECORD
