Metadata-Version: 2.1
Name: thoryvos
Version: 1.0.5
Summary: The All-In One Cryptographic Toolkit
Home-page: https://github.com/freakingrocky/thoryvos
Author: Rakshan Sharma
Author-email: rakshan793@gmail.com
License: MIT
Download-URL: https://github.com/freakingrocky/thoryvos/build/dist/thoryvos-1.0.2.tar.gz
Keywords: Cryptography,Crypto,Audio Cryptography,Stagongraphy,Steganographer,Audio Steganography,Cryptographic Toolkit,File Sharing,Anonymous File Sharing
Platform: UNKNOWN
Classifier: Development Status :: 5 - Production/Stable
Classifier: Intended Audience :: Developers
Classifier: Intended Audience :: End Users/Desktop
Classifier: Intended Audience :: Other Audience
Classifier: Intended Audience :: Science/Research
Classifier: Topic :: Communications :: File Sharing
Classifier: Topic :: Multimedia :: Sound/Audio
Classifier: Topic :: Multimedia :: Sound/Audio :: Conversion
Classifier: Topic :: Security
Classifier: Topic :: Security :: Cryptography
Classifier: License :: OSI Approved :: MIT License
Classifier: Programming Language :: Python :: 3.7
Classifier: Programming Language :: Python :: 3.8
Classifier: Programming Language :: Python :: 3.9
Classifier: Programming Language :: Python :: 3.10
Requires-Dist: PySide2
Requires-Dist: pycryptodome
Requires-Dist: argparse
Requires-Dist: termcolor
Requires-Dist: PyWave
Requires-Dist: SoundFile
Requires-Dist: anonfile
